flask_session_azure/__init__.py
flask_session_azure/storage_account.py
flask_session_azure/storage_account_session.py
flask_session_azure_c-0.4.5.dist-info/LICENSE
flask_session_azure_c-0.4.5.dist-info/METADATA
flask_session_azure_c-0.4.5.dist-info/WHEEL
flask_session_azure_c-0.4.5.dist-info/top_level.txt
flask_session_azure_c-0.4.5.dist-info/RECORD
