Metadata-Version: 2.1
Name: flask-session-azure-c
Version: 0.4.5
Summary: Flask Session using Azure Table Storage or CosmosDB table API
Home-page: https://github.com/bassmandan/FlaskAzureTableSession
Author: Claas Diederichs, Daniel Harding
Author-email: 
License: MIT
Classifier: Framework :: Flask
Classifier: Programming Language :: Python :: 3.6
Classifier: Programming Language :: Python :: 3.7
Classifier: Programming Language :: Python :: 3.8
Classifier: Programming Language :: Python :: 3.9
Classifier: License :: OSI Approved :: MIT License
Classifier: Operating System :: OS Independent
Requires-Python: >=3.6
License-File: LICENSE
Requires-Dist: azure-data-tables
Requires-Dist: pycryptodomex ~=3.9.7
Requires-Dist: flask
